lab_auto_pulumi/__init__.py
lab_auto_pulumi/constants.py
lab_auto_pulumi/ec2.py
lab_auto_pulumi/lib.py
lab_auto_pulumi/py.typed
lab_auto_pulumi/workload.py
lab_auto_pulumi/organization/__init__.py
lab_auto_pulumi/organization/info.py
lab_auto_pulumi/permissions/__init__.py
lab_auto_pulumi/permissions/lib.py
lab_auto_pulumi/permissions/permissions.py
lab_auto_pulumi/s3/__init__.py
lab_auto_pulumi/s3/bucket.py
lab_auto_pulumi-0.1.18.dist-info/METADATA
lab_auto_pulumi-0.1.18.dist-info/WHEEL
lab_auto_pulumi-0.1.18.dist-info/top_level.txt
lab_auto_pulumi-0.1.18.dist-info/RECORD
