Metadata-Version: 2.4
Name: lab-auto-pulumi
Version: 0.1.18
Summary: Pulumi helpers. Especially useful for tooling created by the LabAutomationAndScreening github organization.
Author: Eli Fine
Classifier: Programming Language :: Python :: 3
Classifier: Programming Language :: Python :: 3.12
Classifier: Programming Language :: Python :: 3.13
Classifier: Programming Language :: Python :: 3.14
Requires-Python: >=3.12.7
Requires-Dist: pulumi>=3.213.0
Requires-Dist: pulumi-aws>=7.15.0
Requires-Dist: pulumi-aws-native>=1.45.0
Requires-Dist: ephemeral-pulumi-deploy>=0.0.6
Requires-Dist: boto3>=1.42.14
Requires-Dist: boto3-stubs[ssm]>=1.42.14
Requires-Dist: pydantic>=2.12.5
